docx_parser_converter-1.0.3.dist-info/METADATA
docx_parser_converter-1.0.3.dist-info/WHEEL
docx_parser_converter-1.0.3.dist-info/entry_points.txt
docx_parser_converter/__init__.py
docx_parser_converter/api.py
docx_parser_converter/converters/__init__.py
docx_parser_converter/converters/common/__init__.py
docx_parser_converter/converters/common/numbering_tracker.py
docx_parser_converter/converters/common/style_resolver.py
docx_parser_converter/converters/html/__init__.py
docx_parser_converter/converters/html/css_generator.py
docx_parser_converter/converters/html/html_converter.py
docx_parser_converter/converters/html/html_document.py
docx_parser_converter/converters/html/image_to_html.py
docx_parser_converter/converters/html/numbering_to_html.py
docx_parser_converter/converters/html/paragraph_to_html.py
docx_parser_converter/converters/html/run_to_html.py
docx_parser_converter/converters/html/table_to_html.py
docx_parser_converter/converters/text/__init__.py
docx_parser_converter/converters/text/numbering_to_text.py
docx_parser_converter/converters/text/paragraph_to_text.py
docx_parser_converter/converters/text/run_to_text.py
docx_parser_converter/converters/text/table_to_text.py
docx_parser_converter/converters/text/text_converter.py
docx_parser_converter/core/__init__.py
docx_parser_converter/core/constants.py
docx_parser_converter/core/docx_reader.py
docx_parser_converter/core/exceptions.py
docx_parser_converter/core/model_utils.py
docx_parser_converter/core/unit_conversion.py
docx_parser_converter/core/xml_extractor.py
docx_parser_converter/core/xml_helpers.py
docx_parser_converter/docx_parsers/__init__.py
docx_parser_converter/docx_parsers/utils.py
docx_parser_converter/docx_to_html/__init__.py
docx_parser_converter/docx_to_html/docx_to_html_converter.py
docx_parser_converter/docx_to_txt/__init__.py
docx_parser_converter/docx_to_txt/docx_to_txt_converter.py
docx_parser_converter/models/__init__.py
docx_parser_converter/models/common/__init__.py
docx_parser_converter/models/common/border.py
docx_parser_converter/models/common/color.py
docx_parser_converter/models/common/indentation.py
docx_parser_converter-1.0.3.dist-info/RECORD
