Metadata-Version: 2.1
Name: docx-parser-converter
Version: 1.0.3
Summary: A library for converting DOCX files to HTML and plain text
Keywords: docx,parser,converter,html,text,word,document,office,ooxml
Author-Email: Omer Hayun <omerha86@gmail.com>
License: MIT
Classifier: Development Status :: 5 - Production/Stable
Classifier: Intended Audience :: Developers
Classifier: License :: OSI Approved :: MIT License
Classifier: Programming Language :: Python :: 3
Classifier: Programming Language :: Python :: 3.10
Classifier: Programming Language :: Python :: 3.11
Classifier: Programming Language :: Python :: 3.12
Classifier: Programming Language :: Python :: 3.13
Classifier: Operating System :: OS Independent
Classifier: Topic :: Office/Business
Classifier: Topic :: Text Processing :: Markup :: HTML
Classifier: Typing :: Typed
Project-URL: Homepage, https://github.com/omer-go/docx-parser-converter
Project-URL: Repository, https://github.com/omer-go/docx-parser-converter
Project-URL: Issues, https://github.com/omer-go/docx-parser-converter/issues
Requires-Python: >=3.10
Requires-Dist: lxml>=5.0.0
Requires-Dist: pydantic>=2.0.0
Provides-Extra: dev
Requires-Dist: pytest>=8.0.0; extra == "dev"
Requires-Dist: pyright>=1.1.400; extra == "dev"
Requires-Dist: ruff>=0.8.0; extra == "dev"
Requires-Dist: lxml-stubs>=0.5.0; extra == "dev"
Requires-Dist: setuptools>=70.0.0; extra == "dev"
